tfa_nightly-0.23.0.dev20240415222534.dist-info/RECORD
tfa_nightly-0.23.0.dev20240415222534.dist-info/LICENSE
tfa_nightly-0.23.0.dev20240415222534.dist-info/WHEEL
tfa_nightly-0.23.0.dev20240415222534.dist-info/top_level.txt
tfa_nightly-0.23.0.dev20240415222534.dist-info/METADATA
tensorflow_addons/options.py
tensorflow_addons/conftest.py
tensorflow_addons/version.py
tensorflow_addons/register.py
tensorflow_addons/__init__.py
tensorflow_addons/activations/lisht.py
tensorflow_addons/activations/tanhshrink.py
tensorflow_addons/activations/sparsemax.py
tensorflow_addons/activations/gelu.py
tensorflow_addons/activations/softshrink.py
tensorflow_addons/activations/mish.py
tensorflow_addons/activations/__init__.py
tensorflow_addons/activations/snake.py
tensorflow_addons/activations/hardshrink.py
tensorflow_addons/activations/rrelu.py
tensorflow_addons/metrics/matthews_correlation_coefficient.py
tensorflow_addons/metrics/multilabel_confusion_matrix.py
tensorflow_addons/metrics/cohens_kappa.py
tensorflow_addons/metrics/streaming_correlations.py
tensorflow_addons/metrics/__init__.py
tensorflow_addons/metrics/utils.py
tensorflow_addons/metrics/f_scores.py
tensorflow_addons/metrics/geometric_mean.py
tensorflow_addons/metrics/hamming.py
tensorflow_addons/metrics/harmonic_mean.py
tensorflow_addons/metrics/r_square.py
tensorflow_addons/losses/npairs.py
tensorflow_addons/losses/contrastive.py
tensorflow_addons/losses/giou_loss.py
tensorflow_addons/losses/__init__.py
tensorflow_addons/losses/sparsemax_loss.py
tensorflow_addons/losses/lifted.py
tensorflow_addons/losses/focal_loss.py
tensorflow_addons/losses/quantiles.py
tensorflow_addons/losses/triplet.py
tensorflow_addons/losses/metric_learning.py
tensorflow_addons/losses/kappa_loss.py
tensorflow_addons/custom_ops/layers/_embedding_bag_ops.so
tensorflow_addons/custom_ops/layers/_correlation_cost_ops.so
tensorflow_addons/custom_ops/image/_image_ops.so
tensorflow_addons/custom_ops/image/_distort_image_ops.so
tensorflow_addons/custom_ops/image/_resampler_ops.so
tensorflow_addons/custom_ops/seq2seq/_beam_search_ops.so
tensorflow_addons/custom_ops/text/_skip_gram_ops.so
tensorflow_addons/custom_ops/text/_parse_time_op.so
tensorflow_addons/layers/poincare.py
