Metadata-Version: 2.1
Name: tfa-nightly
Version: 0.23.0.dev20240415222534
Summary: TensorFlow Addons.
Home-page: UNKNOWN
Author: Google Inc.
Author-email: opensource@google.com
License: Apache 2.0
Keywords: tensorflow addons machine learning
Platform: UNKNOWN
Classifier: Development Status :: 4 - Beta
Classifier: Intended Audience :: Developers
Classifier: Intended Audience :: Education
Classifier: Intended Audience :: Science/Research
Classifier: License :: OSI Approved :: Apache Software License
Classifier: Programming Language :: Python :: 3
Classifier: Programming Language :: Python :: 3.9
Classifier: Programming Language :: Python :: 3.10
Classifier: Programming Language :: Python :: 3.11
Classifier: Topic :: Scientific/Engineering :: Mathematics
Classifier: Topic :: Software Development :: Libraries :: Python Modules
Classifier: Topic :: Software Development :: Libraries
Requires-Dist: packaging
Requires-Dist: typeguard (<3.0.0,>=2.7)
Provides-Extra: tensorflow
Requires-Dist: tensorflow (<2.16.0,>=2.13.0) ; extra == 'tensorflow'
Provides-Extra: tensorflow-cpu
Requires-Dist: tensorflow-cpu (<2.16.0,>=2.13.0) ; extra == 'tensorflow-cpu'
Provides-Extra: tensorflow-gpu
Requires-Dist: tensorflow-gpu (<2.16.0,>=2.13.0) ; extra == 'tensorflow-gpu'
